satnogsclient/__init__.py
satnogsclient/_version.py
satnogsclient/config.py
satnogsclient/main.py
satnogsclient/settings.py
satnogsclient/observer/__init__.py
satnogsclient/observer/commsocket.py
satnogsclient/observer/observer.py
satnogsclient/observer/orbital.py
satnogsclient/observer/udpsocket.py
satnogsclient/observer/worker.py
satnogsclient/scheduler/__init__.py
satnogsclient/scheduler/tasks.py
satnogsclient/upsat/__init__.py
satnogsclient/upsat/ecss_logic_utils.py
satnogsclient/upsat/gnuradio_handler.py
satnogsclient/upsat/hldlc.py
satnogsclient/upsat/large_data_service.py
satnogsclient/upsat/packet.py
satnogsclient/upsat/packet_settings.py
satnogsclient/upsat/serial_handler.py
satnogsclient/upsat/tx_handler.py
satnogsclient/upsat/wod.py
satnogsclient/web/__init__.py
satnogsclient/web/app.py
satnogsclient/web/weblogger.py
satnogsclient/web/static/favicon.ico
satnogsclient/web/static/css/app.css
satnogsclient/web/static/css/bootstrap-datetimepicker.css
satnogsclient/web/static/css/bootstrap-switch.css
satnogsclient/web/static/css/bootstrap-theme.css.map
satnogsclient/web/static/css/bootstrap-theme.min.css
satnogsclient/web/static/css/bootstrap.css.map
satnogsclient/web/static/css/bootstrap.min.css
satnogsclient/web/static/fonts/glyphicons-halflings-regular.eot
satnogsclient/web/static/fonts/glyphicons-halflings-regular.svg
satnogsclient/web/static/fonts/glyphicons-halflings-regular.ttf
satnogsclient/web/static/fonts/glyphicons-halflings-regular.woff
satnogsclient/web/static/fonts/glyphicons-halflings-regular.woff2
satnogsclient/web/static/img/satnogs_client.png
satnogsclient/web/static/js/FileSaver.js
satnogsclient/web/static/js/bootstrap-datetimepicker.js
satnogsclient/web/static/js/bootstrap-switch.js
satnogsclient/web/static/js/bootstrap.min.js
satnogsclient/web/static/js/jquery-1.11.3.min.js
satnogsclient/web/static/js/jquery-3.0.0.min.js
satnogsclient/web/static/js/js.cookie.js
satnogsclient/web/static/js/livestamp.min.js
satnogsclient-0.9.1.dist-info/LICENSE
satnogsclient-0.9.1.dist-info/METADATA
satnogsclient-0.9.1.dist-info/WHEEL
satnogsclient-0.9.1.dist-info/entry_points.txt
satnogsclient-0.9.1.dist-info/top_level.txt
satnogsclient-0.9.1.dist-info/RECORD
